gam/__init__.py
gam/__main__.py
gam/cacerts.pem
gam/cbcm-v1.1beta1.json
gam/contactdelegation-v1.json
gam/datastudio-v1.json
gam/meet-v2beta.json
gam/serviceaccountlookup-v1.json
gam/atom/__init__.py
gam/atom/auth.py
gam/atom/client.py
gam/atom/core.py
gam/atom/data.py
gam/atom/http.py
gam/atom/http_core.py
gam/atom/http_interface.py
gam/atom/mock_http.py
gam/atom/mock_http_core.py
gam/atom/mock_service.py
gam/atom/service.py
gam/atom/token_store.py
gam/atom/url.py
gam/gamlib/__init__.py
gam/gamlib/glaction.py
gam/gamlib/glapi.py
gam/gamlib/glcfg.py
gam/gamlib/glclargs.py
gam/gamlib/glentity.py
gam/gamlib/glgapi.py
gam/gamlib/glgdata.py
gam/gamlib/glglobals.py
gam/gamlib/glindent.py
gam/gamlib/glmsgs.py
gam/gamlib/glskus.py
gam/gamlib/gluprop.py
gam/gamlib/glverlibs.py
gam/gamlib/yubikey.py
gam/gdata/__init__.py
gam/gdata/service.py
gam/gdata/urlfetch.py
gam/gdata/alt/__init__.py
gam/gdata/alt/app_engine.py
gam/gdata/alt/appengine.py
gam/gdata/apps/__init__.py
gam/gdata/apps/service.py
gam/gdata/apps/audit/__init__.py
gam/gdata/apps/audit/service.py
gam/gdata/apps/contacts/__init__.py
gam/gdata/apps/contacts/service.py
gam7-7.32.7.dist-info/METADATA
gam7-7.32.7.dist-info/WHEEL
gam7-7.32.7.dist-info/entry_points.txt
gam7-7.32.7.dist-info/licenses/LICENSE
gam7-7.32.7.dist-info/RECORD
