Metadata-Version: 2.4
Name: gam7
Version: 7.32.7
Summary: CLI tool to manage Google Workspace
Project-URL: Homepage, https://github.com/GAM-team/GAM
Project-URL: Issues, https://github.com/GAM-team/GAM/issues
Project-URL: Discussion, https://groups.google.com/group/google-apps-manager
Project-URL: Chat, https://git.io/gam-chat
Author-email: Jay Lee <jay0lee@gmail.com>, Ross Scroggs <Ross.Scroggs@gmail.com>
License: Apache License (2.0)
License-File: LICENSE
Classifier: Operating System :: OS Independent
Classifier: Programming Language :: Python :: 3
Classifier: Programming Language :: Python :: 3 :: Only
Classifier: Programming Language :: Python :: 3.9
Classifier: Programming Language :: Python :: 3.10
Classifier: Programming Language :: Python :: 3.11
Classifier: Programming Language :: Python :: 3.12
Classifier: Programming Language :: Python :: 3.13
Requires-Python: >=3.10
Requires-Dist: arrow>=1.3.0
Requires-Dist: chardet>=5.2.0
Requires-Dist: cryptography==46.0.3
Requires-Dist: distro; sys_platform == 'linux'
Requires-Dist: filelock>=3.18.0
Requires-Dist: google-api-python-client>=2.167.0
Requires-Dist: google-auth-httplib2>=0.2.0
Requires-Dist: google-auth-oauthlib>=1.2.2
Requires-Dist: google-auth>=2.39.0
Requires-Dist: httplib2>=0.31.0
Requires-Dist: lxml>=5.4.0
Requires-Dist: passlib>=1.7.4
Requires-Dist: pathvalidate>=3.2.3
Requires-Dist: pysocks>=1.7.1
Provides-Extra: yubikey
Requires-Dist: yubikey-manager>=5.6.1; extra == 'yubikey'
